[
    {
        "model": "gamerraterapi.game",
        "pk": 1,
        "fields": {
            "title": "BANG",
            "description": "LA CARDAGAMA MAS FINA",
            "designer": "La Vinnie Videci",
            "year_realeased": 1997,
            "number_of_players": 8,
            "time_to_play": 20000,
            "age_recommendation": 12
        }
    },
    {
        "model": "gamerraterapi.game",
        "pk": 2,
        "fields": {
            "title": "Yacht-ZEE",
            "description": "Relax. on a boat. play a game",
            "designer": "Donatella Versaci",
            "year_realeased": 1997,
            "number_of_players": 4,
            "time_to_play": 2004533,
            "age_recommendation": 5
        }
    },
    {
        "model": "gamerraterapi.game",
        "pk": 3,
        "fields": {
            "title": "D&D&D",
            "description": "Dungeons and Dragons and DONUTS",
            "designer": "Some wiseguy",
            "year_realeased": 2004,
            "number_of_players": 4,
            "time_to_play": 2939433,
            "age_recommendation": 15
        }
    },
    {
        "model": "gamerraterapi.game",
        "pk": 4,
        "fields": {
            "title": "Jungle Rumble",
            "description": "Time to rumble. In the fricken jungle",
            "designer": "Marvel Smash Bros Inc",
            "year_realeased": 1987,
            "number_of_players": 2,
            "time_to_play":293944,
            "age_recommendation": 14
        }
    },
    {
        "model": "gamerraterapi.game",
        "pk": 5,
        "fields": {
            "title": "SnackTime",
            "description": "Everybody needs a lil treat yeah?",
            "designer": "Afsnackinstan",
            "year_realeased": 2000,
            "number_of_players": 15,
            "time_to_play": 233445,
            "age_recommendation": 5
        }
    },
    {
        "model": "gamerraterapi.game",
        "pk": 5,
        "fields": {
            "title": "SnackTime",
            "description": "Everybody needs a lil treat yeah?",
            "designer": "Afsnackinstan",
            "year_realeased": 2000,
            "number_of_players": 15,
            "time_to_play": 23000,
            "age_recommendation": 5
        }
    },
    {
        "model": "gamerraterapi.game",
        "pk": 6,
        "fields": {
            "title": "RAGE",
            "description": "",
            "designer": "dis boy",
            "year_realeased": 1990,
            "number_of_players": 15,
            "time_to_play": 23300,
            "age_recommendation": 20
        }
    },
    {
        "model": "gamerraterapi.game",
        "pk": 7,
        "fields": {
            "title": "NEXFLIX N PILLZ",
            "description": "",
            "designer": "that gal",
            "year_realeased": 2020,
            "number_of_players": 10,
            "time_to_play": 34000,
            "age_recommendation": 20
        }
    }
]